spek/__init__.py
spek/__main__.py
spek/detector.py
spek-0.0.4.dist-info/licenses/License
spek-0.0.4.dist-info/METADATA
spek-0.0.4.dist-info/WHEEL
spek-0.0.4.dist-info/entry_points.txt
spek-0.0.4.dist-info/top_level.txt
spek-0.0.4.dist-info/RECORD
