Metadata-Version: 2.4
Name: SPEK
Version: 0.0.4
Summary: SPEK: Simple Python Extraction Kit - Easy YOLOv8 Object Detection
Author: Rudransh Joshi
Author-email: rudransh20septmber@gmail.com
Classifier: Programming Language :: Python :: 3
Classifier: License :: OSI Approved :: MIT License
Classifier: Operating System :: OS Independent
Classifier: Topic :: Scientific/Engineering :: Artificial Intelligence
Classifier: Topic :: Multimedia :: Video :: Capture
Classifier: Topic :: Multimedia :: Graphics :: Capture :: Digital Camera
Requires-Python: >=3.7
License-File: License
Requires-Dist: opencv-python
Requires-Dist: ultralytics>=8.0.0
Dynamic: author
Dynamic: author-email
Dynamic: classifier
Dynamic: description
Dynamic: description-content-type
Dynamic: license-file
Dynamic: requires-dist
Dynamic: requires-python
Dynamic: summary
